poll_schumann/__init__.py
poll_schumann/data/aircraft_engine_params.csv
poll_schumann/engine_loader.py
poll_schumann/parameters/__init__.py
poll_schumann/parameters/aircraft_parameters.py
poll_schumann/parameters/atmospheric_parameters.py
poll_schumann/parameters/constants.py
poll_schumann/parameters/jet.py
poll_schumann/parameters/operational_limits.py
poll_schumann/parameters/units.py
poll_schumann/pollschumann.py
poll_schumann/utils/__init__.py
poll_schumann/utils/aero.py
poll_schumann-0.1.3.dist-info/METADATA
poll_schumann-0.1.3.dist-info/WHEEL
poll_schumann-0.1.3.dist-info/RECORD
