Metadata-Version: 2.1
Name: poll_schumann
Version: 0.1.3
Summary: Implementation of Poll-Schumann aircraft performance model in Python.
License: MIT
Author: nestorcarmona
Author-email: nestor.carmona97@gmail.com
Requires-Python: >=3.8,<4.0
Classifier: License :: OSI Approved :: MIT License
Classifier: Programming Language :: Python :: 3
Classifier: Programming Language :: Python :: 3.8
Classifier: Programming Language :: Python :: 3.9
Classifier: Programming Language :: Python :: 3.10
Classifier: Programming Language :: Python :: 3.11
Classifier: Programming Language :: Python :: 3.12
Requires-Dist: numpy (>=1.20.1)
Requires-Dist: pandas (>=1.2.0)
